<?xml version="1.0" encoding="utf-8"?>
<TextureAtlas imagePath="tabiandyuri.png">
	<!-- Created with Adobe Animate version 20.0.3.25487 -->
	<!-- http://www.adobe.com/products/animate.html -->
	<SubTexture name="Tabi Yuri together hueh0000" x="10" y="10" width="805" height="748"/>
	<SubTexture name="Tabi Yuri together hueh0001" x="10" y="10" width="805" height="748"/>
	<SubTexture name="Tabi Yuri together hueh0002" x="825" y="10" width="805" height="748"/>
	<SubTexture name="Tabi Yuri together hueh0003" x="825" y="10" width="805" height="748"/>
	<SubTexture name="Tabi Yuri together hueh0004" x="10" y="10" width="805" height="748"/>
	<SubTexture name="Tabi Yuri together hueh0005" x="10" y="10" width="805" height="748"/>
	<SubTexture name="Tabi Yuri together hueh0006" x="10" y="10" width="805" height="748"/>
	<SubTexture name="Tabi Yuri together hueh0007" x="825" y="10" width="805" height="748"/>
	<SubTexture name="Tabi Yuri together hueh0008" x="825" y="10" width="805" height="748"/>
	<SubTexture name="Tabi Yuri together hueh0009" x="10" y="10" width="805" height="748"/>
	<SubTexture name="Tabi Yuri together hueh0010" x="10" y="10" width="805" height="748"/>
	<SubTexture name="Tabi Yuri together hueh0011" x="10" y="10" width="805" height="748"/>
	<SubTexture name="Tabi Yuri together hueh0012" x="10" y="10" width="805" height="748"/>
	<SubTexture name="Tabi Yuri together hueh0013" x="825" y="10" width="805" height="748"/>
	<SubTexture name="Tabi Yuri together hueh0014" x="1640" y="10" width="805" height="748"/>
	<SubTexture name="Tabi Yuri together hueh0015" x="2455" y="10" width="805" height="748"/>
	<SubTexture name="Tabi Yuri together hueh0016" x="3270" y="10" width="805" height="748"/>
	<SubTexture name="Tabi Yuri together hueh0017" x="4085" y="10" width="805" height="748"/>
	<SubTexture name="Tabi Yuri together hueh0018" x="4900" y="10" width="805" height="748"/>
	<SubTexture name="Tabi Yuri together hueh0019" x="5715" y="10" width="805" height="748"/>
	<SubTexture name="Tabi Yuri together hueh0020" x="6530" y="10" width="805" height="748"/>
	<SubTexture name="Tabi Yuri together hueh0021" x="7345" y="10" width="805" height="748"/>
	<SubTexture name="Tabi Yuri together hueh0022" x="10" y="768" width="805" height="748"/>
	<SubTexture name="Tabi Yuri together hueh0023" x="825" y="768" width="805" height="748"/>
	<SubTexture name="Tabi Yuri together hueh0024" x="825" y="768" width="805" height="748"/>
	<SubTexture name="Tabi Yuri together hueh0025" x="1640" y="768" width="805" height="748"/>
	<SubTexture name="Tabi Yuri together hueh0026" x="1640" y="768" width="805" height="748"/>
	<SubTexture name="Tabi Yuri together hueh0027" x="825" y="768" width="805" height="748"/>
	<SubTexture name="Tabi Yuri together hueh0028" x="825" y="768" width="805" height="748"/>
	<SubTexture name="Tabi Yuri together hueh0029" x="825" y="768" width="805" height="748"/>
	<SubTexture name="Tabi Yuri together hueh0030" x="1640" y="768" width="805" height="748"/>
	<SubTexture name="Tabi Yuri together hueh0031" x="2455" y="768" width="805" height="748"/>
	<SubTexture name="Tabi Yuri together hueh0032" x="3270" y="768" width="805" height="748"/>
	<SubTexture name="Tabi Yuri together hueh0033" x="4085" y="768" width="805" height="748"/>
	<SubTexture name="Tabi Yuri together hueh0034" x="4900" y="768" width="805" height="748"/>
	<SubTexture name="Tabi Yuri together hueh0035" x="5715" y="768" width="805" height="748"/>
	<SubTexture name="Tabi Yuri together hueh0036" x="5715" y="768" width="805" height="748"/>
	<SubTexture name="Tabi Yuri together hueh0037" x="6530" y="768" width="805" height="748"/>
	<SubTexture name="Tabi Yuri together hueh0038" x="7345" y="768" width="805" height="748"/>
	<SubTexture name="Tabi Yuri together hueh0039" x="10" y="1526" width="805" height="748"/>
	<SubTexture name="Tabi Yuri together hueh0040" x="825" y="1526" width="805" height="748"/>
	<SubTexture name="Tabi Yuri together hueh0041" x="1640" y="1526" width="805" height="748"/>
	<SubTexture name="Tabi Yuri together hueh0042" x="1640" y="1526" width="805" height="748"/>
	<SubTexture name="Tabi Yuri together hueh0043" x="2455" y="1526" width="805" height="748"/>
	<SubTexture name="Tabi Yuri together hueh0044" x="2455" y="1526" width="805" height="748"/>
	<SubTexture name="Tabi Yuri together hueh0045" x="3270" y="1526" width="805" height="748"/>
	<SubTexture name="Tabi Yuri together hueh0046" x="3270" y="1526" width="805" height="748"/>
	<SubTexture name="Tabi Yuri together hueh0047" x="3270" y="1526" width="805" height="748"/>
	<SubTexture name="Tabi Yuri together hueh0048" x="2455" y="1526" width="805" height="748"/>
	<SubTexture name="Tabi Yuri together hueh0049" x="2455" y="1526" width="805" height="748"/>
	<SubTexture name="Tabi Yuri together hueh0050" x="3270" y="1526" width="805" height="748"/>
	<SubTexture name="Tabi Yuri together hueh0051" x="3270" y="1526" width="805" height="748"/>
	<SubTexture name="Tabi Yuri together hueh0052" x="3270" y="1526" width="805" height="748"/>
	<SubTexture name="Tabi Yuri together hueh0053" x="2455" y="1526" width="805" height="748"/>
	<SubTexture name="Tabi Yuri together hueh0054" x="2455" y="1526" width="805" height="748"/>
	<SubTexture name="Tabi Yuri together hueh0055" x="3270" y="1526" width="805" height="748"/>
	<SubTexture name="Tabi Yuri together hueh0056" x="3270" y="1526" width="805" height="748"/>
	<SubTexture name="Tabi Yuri together hueh0057" x="3270" y="1526" width="805" height="748"/>
	<SubTexture name="Tabi Yuri together hueh0058" x="2455" y="1526" width="805" height="748"/>
	<SubTexture name="Tabi Yuri together hueh0059" x="4085" y="1526" width="805" height="748"/>
	<SubTexture name="Tabi Yuri together hueh0060" x="4085" y="1526" width="805" height="748"/>
	<SubTexture name="Tabi Yuri together hueh0061" x="4900" y="1526" width="805" height="748"/>
	<SubTexture name="Tabi Yuri together hueh0062" x="5715" y="1526" width="805" height="748"/>
	<SubTexture name="Tabi Yuri together hueh0063" x="5715" y="1526" width="805" height="748"/>
	<SubTexture name="Tabi Yuri together hueh0064" x="6530" y="1526" width="805" height="748"/>
	<SubTexture name="Tabi Yuri together hueh0065" x="6530" y="1526" width="805" height="748"/>
	<SubTexture name="Tabi Yuri together hueh0066" x="5715" y="1526" width="805" height="748"/>
	<SubTexture name="Tabi Yuri together hueh0067" x="7345" y="1526" width="805" height="748"/>
	<SubTexture name="Tabi Yuri together hueh0068" x="10" y="2284" width="805" height="748"/>
	<SubTexture name="Tabi Yuri together hueh0069" x="825" y="2284" width="805" height="748"/>
	<SubTexture name="Tabi Yuri together hueh0070" x="825" y="2284" width="805" height="748"/>
	<SubTexture name="Tabi Yuri together hueh0071" x="10" y="10" width="805" height="748"/>
	<SubTexture name="Tabi Yuri together hueh0072" x="10" y="10" width="805" height="748"/>
</TextureAtlas>
