{
	"animations": [
		{
			"offsets": [
				0,
				0
			],
			"indices": [],
			"fps": 24,
			"anim": "idle",
			"loop": false,
			"name": "Monika Returns Idle"
		},
		{
			"offsets": [
				-105,
				13
			],
			"indices": [],
			"fps": 24,
			"anim": "singUP",
			"loop": false,
			"name": "Monika Returns Up"
		},
		{
			"offsets": [
				-30,
				-10
			],
			"indices": [],
			"fps": 24,
			"anim": "singRIGHT",
			"loop": false,
			"name": "Monika Returns Right"
		},
		{
			"offsets": [
				-30,
				-64
			],
			"indices": [],
			"fps": 24,
			"anim": "singDOWN",
			"loop": false,
			"name": "Monika Returns Down"
		},
		{
			"offsets": [
				-20,
				39
			],
			"indices": [],
			"fps": 24,
			"anim": "singLEFT",
			"loop": false,
			"name": "Monika Returns Left"
		}
	],
	"no_antialiasing": false,
	"image": "characters/monika/Doki_MonikaValentine_Assets",
	"position": [
		0,
		-350
	],
	"healthicon": "monika",
	"flip_x": false,
	"healthbar_colors": [
		140,
		212,
		101
	],
	"camera_position": [
		0,
		0
	],
	"sing_duration": 6,
	"scale": 0.9
}