{
	"startingMusic": "sayoc",
	"initStyle": "normal",
	"dialogue": 
	[
		{
			"isCommand": false,
			"name": "yuri",
			"expression": "neutral",
			"string": "\"It appears that we have visitors.\"",
			"key": "rcIntro1",
			"side": "left"
		},
		{
			"isCommand": false,
			"name": "natsuki",
			"expression": "hmmph",
			"string": "\"Seriously, Sayori? You brought a boy to the club?\"",
			"key": "rcIntro2",
			"side": "left"
		},
		{
			"isCommand": false,
			"name": "sayori",
			"expression": "ehh",
			"string": "\"Hey- I wasn’t expecting anyone new. We haven’t even put out fliers for the club yet!\"",
			"key": "rcIntro3",
			"side": "left"
		},
		{
			"isCommand": false,
			"name": "sayori",
			"expression": "neutral",
			"string": "\"But look, Natsuki! We have another girl too!\"",
			"key": "rcIntro4",
			"side": "left"
		},
		{
			"isCommand": false,
			"name": "gf",
			"expression": "neutral",
			"string": "*empty thoughts*",
			"key": "rcIntro5",
			"side": "right"
		},
		{
			"isCommand": false,
			"name": "sayori",
			"expression": "ehh",
			"string": "\"Ehehe, if I knew we were expecting more members- I would've asked Natsuki to bake some welcome cupcakes!\"",
			"key": "rcIntro6",
			"side": "left"
		},
		{
			"isCommand": false,
			"name": "sayori",
			"expression": "happ",
			"string": "\"Oh! And maybe I could've asked Yuri to make tea as well!\"",
			"key": "rcIntro7",
			"side": "left"
		},
		{
			"isCommand": false,
			"name": "sayori",
			"expression": "happ",
			"string": "\"I need to write this down for later: 'Plan Tea Party for Club Soon'\"",
			"key": "rcIntro8",
			"side": "left"
		},
		{
			"isCommand": false,
			"name": "yuri",
			"expression": "smile",
			"string": "\"Sounds like you’re already very excited about our new guests. You haven’t even asked for their names yet-\"",
			"key": "rcIntro9",
			"side": "right"
		},
		{
			"isCommand": false,
			"name": "sayori",
			"expression": "ehh",
			"string": "\"Ah, right! Eheh, silly me. What’re your names, new literature club attendees?\"",
			"key": "rcIntro10",
			"side": "left"
		},
		{
			"isCommand": false,
			"name": "bf",
			"expression": "beep",
			"string": "\"Beep skee!\"",
			"key": "rcIntro11",
			"side": "right"
		},
		{
			"isCommand": false,
			"name": "gf",
			"expression": "yeah",
			"string": "*happy gesture*",
			"key": "rcIntro12",
			"side": "right"
		},
		{
			"isCommand": false,
			"name": "sayori",
			"expression": "happ",
			"string": "\"You two are Boyfriend and Girlfriend? Aww, you look so cute together!!!\"",
			"key": "rcIntro13",
			"side": "left"
		},
		{
			"isCommand": false,
			"name": "natsuki",
			"expression": "neutral",
			"string": "\"...that’s cute and all, but like, what are your names?\"",
			"key": "rcIntro14",
			"side": "left"
		},
		{
			"isCommand": false,
			"name": "bf",
			"expression": "beep",
			"string": "\"Beep skee!\"",
			"key": "rcIntro15",
			"side": "right"
		},
		{
			"isCommand": false,
			"name": "gf",
			"expression": "yeah",
			"string": "*another happy gesture*",
			"key": "rcIntro16",
			"side": "right"
		},
		{
			"isCommand": false,
			"name": "natsuki",
			"expression": "angy",
			"string": "\"Yes, we know that you guys are dating! We wanna know your NAMES!\"",
			"key": "rcIntro17",
			"side": "left"
		},
		{
			"isCommand": false,
			"name": "bf",
			"expression": "neutral",
			"string": "\"Bee dee skee dep!\"",
			"key": "rcIntro18",
			"side": "right"
		},
		{
			"isCommand": false,
			"name": "natsuki",
			"expression": "hmmph",
			"string": "\"...I don’t like them already.\"",
			"key": "rcIntro19",
			"side": "left"
		},
		{
			"isCommand": false,
			"name": "natsuki",
			"expression": "hmmph",
			"string": "\"They’re already messing with me!\"",
			"key": "rcIntro20",
			"side": "left"
		},
		{
			"isCommand": false,
			"name": "yuri",
			"expression": "ehh",
			"string": "\"Natsuki! Not so harsh...\"",
			"key": "rcIntro21",
			"side": "left"
		},
		{
			"isCommand": false,
			"name": "natsuki",
			"expression": "hmmph",
			"string": "\"Hmph.\"",
			"key": "rcIntro22",
			"side": "left"
		},
		{
			"isCommand": false,
			"name": "sayori",
			"expression": "ehh",
			"string": "\"Eheheh... I’m sorry about that. If you don’t want to tell us your names, that’s ok!\"",
			"key": "rcIntro23",
			"side": "left"
		},
		{
			"isCommand": false,
			"name": "sayori",
			"expression": "happ",
			"string": "\"I’m Sayori!\"",
			"key": "rcIntro24",
			"side": "left"
		},
		{
			"isCommand": false,
			"name": "sayori",
			"expression": "neutral",
			"string": "\"That lovely lavender lady over there is Yuri, and Natsuki is the one who’s real sassy today.\"",
			"key": "rcIntro25",
			"side": "left"
		},
		{
			"isCommand": false,
			"name": "yuri",
			"expression": "neutral",
			"string": "\"With introductions aside... may we ask what these microphones are for?\"",
			"key": "rcIntro26",
			"side": "left"
		},
		{
			"isCommand": false,
			"name": "sayori",
			"expression": "neutral",
			"string": "\"I was just about to ask that.\"",
			"key": "rcIntro27",
			"side": "left"
		},
		{
			"isCommand": false,
			"name": "sayori",
			"expression": "ehh",
			"string": "\"I hope you didn’t confuse this place with the music club-\"",
			"key": "rcIntro28",
			"side": "left"
		},
		{
			"isCommand": false,
			"name": "bf",
			"expression": "beep",
			"string": "\"Boop dee!\"",
			"key": "rcIntro29",
			"side": "right"
		},
		{
			"isCommand": false,
			"name": "yuri",
			"expression": "neutral",
			"string": "\"...you really want to sing with us?\"",
			"key": "rcIntro30",
			"side": "left"
		},
		{
			"isCommand": false,
			"name": "yuri",
			"expression": "blush",
			"string": "\"I’m... not sure how comfortable I’d feel doing that-\"",
			"key": "rcIntro31",
			"side": "left"
		},
		{
			"isCommand": false,
			"name": "bf",
			"expression": "beep",
			"string": "\"Skee dep doop!\"",
			"key": "rcIntro32",
			"side": "right"
		},
		{
			"isCommand": false,
			"name": "yuri",
			"expression": "blush",
			"string": "\"Wh-what do you mean I have to?!\"",
			"key": "rcIntro33",
			"side": "left"
		},
		{
			"isCommand": true,
			"name": "hideright"
		},
		{
			"isCommand": false,
			"name": "sayori",
			"expression": "neutral",
			"string": "\"You know, we’ve been working so hard on writing and poems lately. I think having a fun singing session with everyone is the perfect break we all need!\"",
			"key": "rcIntro34",
			"side": "left"
		},
		{
			"isCommand": false,
			"name": "yuri",
			"expression": "blush",
			"string": "\"-!\"",
			"side": "right"
		},
		{
			"isCommand": false,
			"name": "sayori",
			"expression": "neutral",
			"string": "\"When you think about it, songs are just poems with music behind them, aren’t they?\"",
			"key": "rcIntro35",
			"side": "left"
		},
		{
			"isCommand": false,
			"name": "sayori",
			"expression": "yeah",
			"string": "\"I bet we’d all be great at this!\"",
			"key": "rcIntro36",
			"side": "left"
		},
		{
			"isCommand": false,
			"name": "yuri",
			"expression": "neutral",
			"string": "\"...\"",
			"side": "right"
		},
		{
			"isCommand": false,
			"name": "natsuki",
			"expression": "neutral",
			"string": "\"...\"",
			"side": "right"
		},
		{
			"isCommand": false,
			"name": "sayori",
			"expression": "yeah",
			"string": "\"Here, I’ll go first!\"",
			"key": "rcIntro37",
			"side": "left"
		}
	]
}