<?xml version="1.0" encoding="utf-8"?>
<TextureAtlas imagePath="gfDanceTitle.png">
	<!-- Created with Adobe Animate version 20.0.3.25487 -->
	<!-- http://www.adobe.com/products/animate.html -->
	<SubTexture name="gfDance0000" x="0" y="0" width="699" height="634" frameX="-2" frameY="-14" frameWidth="703" frameHeight="648"/>
	<SubTexture name="gfDance0001" x="709" y="0" width="703" height="634" frameX="0" frameY="-14" frameWidth="703" frameHeight="648"/>
	<SubTexture name="gfDance0002" x="1422" y="0" width="703" height="632" frameX="0" frameY="-16" frameWidth="703" frameHeight="648"/>
	<SubTexture name="gfDance0003" x="2135" y="0" width="699" height="632" frameX="-2" frameY="-16" frameWidth="703" frameHeight="648"/>
	<SubTexture name="gfDance0004" x="2844" y="0" width="699" height="635" frameX="-2" frameY="-13" frameWidth="703" frameHeight="648"/>
	<SubTexture name="gfDance0005" x="0" y="645" width="699" height="635" frameX="-2" frameY="-13" frameWidth="703" frameHeight="648"/>
	<SubTexture name="gfDance0006" x="709" y="645" width="699" height="637" frameX="-2" frameY="-11" frameWidth="703" frameHeight="648"/>
	<SubTexture name="gfDance0007" x="1418" y="645" width="699" height="648" frameX="-2" frameY="0" frameWidth="703" frameHeight="648"/>
	<SubTexture name="gfDance0008" x="1418" y="645" width="699" height="648" frameX="-2" frameY="0" frameWidth="703" frameHeight="648"/>
	<SubTexture name="gfDance0009" x="1418" y="645" width="699" height="648" frameX="-2" frameY="0" frameWidth="703" frameHeight="648"/>
	<SubTexture name="gfDance0010" x="2127" y="645" width="699" height="648" frameX="-2" frameY="0" frameWidth="703" frameHeight="648"/>
	<SubTexture name="gfDance0011" x="2127" y="645" width="699" height="648" frameX="-2" frameY="0" frameWidth="703" frameHeight="648"/>
	<SubTexture name="gfDance0012" x="2127" y="645" width="699" height="648" frameX="-2" frameY="0" frameWidth="703" frameHeight="648"/>
	<SubTexture name="gfDance0013" x="2836" y="645" width="699" height="648" frameX="-2" frameY="0" frameWidth="703" frameHeight="648"/>
	<SubTexture name="gfDance0014" x="2836" y="645" width="699" height="648" frameX="-2" frameY="0" frameWidth="703" frameHeight="648"/>
	<SubTexture name="gfDance0015" x="0" y="1303" width="699" height="636" frameX="-2" frameY="-12" frameWidth="703" frameHeight="648"/>
	<SubTexture name="gfDance0016" x="709" y="1303" width="703" height="636" frameX="0" frameY="-12" frameWidth="703" frameHeight="648"/>
	<SubTexture name="gfDance0017" x="1422" y="1303" width="703" height="636" frameX="0" frameY="-12" frameWidth="703" frameHeight="648"/>
	<SubTexture name="gfDance0018" x="2135" y="1303" width="699" height="636" frameX="-2" frameY="-12" frameWidth="703" frameHeight="648"/>
	<SubTexture name="gfDance0019" x="2844" y="1303" width="699" height="637" frameX="-2" frameY="-11" frameWidth="703" frameHeight="648"/>
	<SubTexture name="gfDance0020" x="0" y="1950" width="699" height="637" frameX="-2" frameY="-11" frameWidth="703" frameHeight="648"/>
	<SubTexture name="gfDance0021" x="709" y="1950" width="699" height="638" frameX="-2" frameY="-10" frameWidth="703" frameHeight="648"/>
	<SubTexture name="gfDance0022" x="1418" y="1950" width="699" height="643" frameX="-2" frameY="-5" frameWidth="703" frameHeight="648"/>
	<SubTexture name="gfDance0023" x="1418" y="1950" width="699" height="643" frameX="-2" frameY="-5" frameWidth="703" frameHeight="648"/>
	<SubTexture name="gfDance0024" x="1418" y="1950" width="699" height="643" frameX="-2" frameY="-5" frameWidth="703" frameHeight="648"/>
	<SubTexture name="gfDance0025" x="2127" y="1950" width="699" height="642" frameX="-2" frameY="-6" frameWidth="703" frameHeight="648"/>
	<SubTexture name="gfDance0026" x="2127" y="1950" width="699" height="642" frameX="-2" frameY="-6" frameWidth="703" frameHeight="648"/>
	<SubTexture name="gfDance0027" x="2127" y="1950" width="699" height="642" frameX="-2" frameY="-6" frameWidth="703" frameHeight="648"/>
	<SubTexture name="gfDance0028" x="2836" y="1950" width="699" height="642" frameX="-2" frameY="-6" frameWidth="703" frameHeight="648"/>
	<SubTexture name="gfDance0029" x="2836" y="1950" width="699" height="642" frameX="-2" frameY="-6" frameWidth="703" frameHeight="648"/>
</TextureAtlas>
